lightkde/__init__.py
lightkde/lightkde.py
tests/__init__.py
tests/test_kde_1d.py
tests/test_kde_2d.py
lightkde-1.0.4.dist-info/LICENSE
lightkde-1.0.4.dist-info/METADATA
lightkde-1.0.4.dist-info/WHEEL
lightkde-1.0.4.dist-info/top_level.txt
lightkde-1.0.4.dist-info/RECORD
