Metadata-Version: 2.1
Name: lightkde
Version: 1.0.4
Summary: Lightning fast, lightweight, and reliable kernel density estimation.
Home-page: https://github.com/TNO/lightkde
Author: Arpad Rozsas
Author-email: rozsasarpi@gmail.com
Classifier: Intended Audience :: Science/Research
Classifier: Programming Language :: Python :: 3.7
Classifier: Programming Language :: Python :: 3.8
Classifier: Programming Language :: Python :: 3.9
Classifier: Programming Language :: Python :: 3.10
Classifier: Programming Language :: Python :: 3.11
Classifier: Topic :: Scientific/Engineering
Classifier: Operating System :: OS Independent
Requires-Python: >=3.7
License-File: LICENSE
Requires-Dist: numpy (<2)
Requires-Dist: scipy (<2)
Provides-Extra: docs
Requires-Dist: matplotlib (<4) ; extra == 'docs'
Requires-Dist: sphinx (<5,>=3) ; extra == 'docs'
Requires-Dist: sphinx-gallery (<1) ; extra == 'docs'
Requires-Dist: sphinx-copybutton (<1) ; extra == 'docs'
Requires-Dist: sphinx-inline-tabs ; extra == 'docs'
Requires-Dist: sphinxcontrib-bibtex (<3) ; extra == 'docs'
Requires-Dist: myst-parser (<1) ; extra == 'docs'
Requires-Dist: furo ; extra == 'docs'
Provides-Extra: lint_type_checks
Requires-Dist: pre-commit ; extra == 'lint_type_checks'
Provides-Extra: tests
Requires-Dist: matplotlib (<4) ; extra == 'tests'
Requires-Dist: pytest ; extra == 'tests'
Requires-Dist: coverage[toml] ; extra == 'tests'
